{
  "folder": "LJS9nI5Bz0zn7oMW",
  "img": "Art%20-%20Items/worn-items/circlet_pharasma_charisma.webp",
  "name": "Headband of Pharizzma +2",
  "system": {
    "description": {
      "value": "<img src=\"Art%20-%20Items/worn-items/circlet_pharasma_charisma.webp\" /><p>This attractive silver headband is decorated with a number of small red and orange gemstones.</p><p>The headband grants the wearer an <em>enhancement bonus</em> to <em>Charisma</em> of +2, +4, or +6. Treat this as a temporary ability bonus for the first 24 hours the headband is worn.</p><h3>Construction</h3><p><strong>Requirements</strong> @UUID[Compendium.pf1.feats.Item.tD76K8QGco9scT0r]{Craft Wondrous Item}, @UUID[Compendium.pf1.spells.Item.d4oubr5bdoo8w1ev]{Eagle's Splendor}; <strong>Cost</strong> 2,000 gp</p>",
      "instructions": "",
      "unidentified": "<p>This attractive silver headband is decorated with a number of small red and orange gemstones.</p>"
    },
    "tags": [],
    "quantity": 1,
    "weight": {
      "value": 1
    },
    "equipped": true,
    "carried": true,
    "price": 4000,
    "size": "med",
    "resizing": true,
    "timeworn": false,
    "artifact": false,
    "identified": true,
    "unidentified": {
      "price": 0,
      "name": "Headband"
    },
    "cursed": false,
    "cl": 8,
    "aura": {
      "custom": false,
      "school": "trs"
    },
    "hp": {
      "base": 10,
      "offset": 0
    },
    "broken": false,
    "hardness": 0,
    "changes": [
      {
        "_id": "SIoTZuf0",
        "formula": "2",
        "target": "cha",
        "type": "enh",
        "operator": "add",
        "priority": 0
      }
    ],
    "changeFlags": {
      "immuneToMorale": false,
      "loseDexToAC": false,
      "noMediumEncumbrance": false,
      "noHeavyEncumbrance": false,
      "mediumArmorFullSpeed": false,
      "heavyArmorFullSpeed": false,
      "lowLightVision": false,
      "seeInvisibility": false,
      "seeInDarkness": false
    },
    "contextNotes": [],
    "actions": [],
    "attackNotes": [],
    "effectNotes": [],
    "uses": {
      "value": null,
      "per": "",
      "autoDeductChargesCost": "",
      "maxFormula": "",
      "rechargeFormula": ""
    },
    "links": {
      "children": [],
      "charges": []
    },
    "tag": "",
    "flags": {
      "boolean": {},
      "dictionary": {}
    },
    "scriptCalls": [],
    "masterwork": false,
    "enh": null,
    "proficient": false,
    "held": "1h",
    "ammo": {
      "type": "",
      "capacity": null,
      "misfire": null,
      "explode": null
    },
    "subType": "wondrous",
    "slot": "headband",
    "equipmentSubtype": "lightArmor",
    "hands": 0,
    "baseTypes": [],
    "armor": {
      "value": 0,
      "dex": null,
      "acp": 0,
      "enh": 0,
      "material": {
        "base": {
          "value": "leather",
          "custom": false
        },
        "normal": {
          "value": "leather",
          "custom": false
        },
        "addon": []
      }
    },
    "spellFailure": 0,
    "showInQuickbar": false,
    "sources": [
      {
        "id": "PZO1123",
        "pages": "248"
      },
      {
        "id": "PZO1110",
        "pages": "516"
      }
    ],
    "nonlethal": false
  },
  "type": "equipment",
  "effects": [],
  "flags": {
    "core": {},
    "item-piles": {
      "item": {}
    },
    "lilhelper": {
      "item": {
        "hideAttacks": false,
        "autoPowerAttack": false,
        "keen": false,
        "skipDialog": 0,
        "rollmodeOverride": "",
        "rollOverride": ""
      }
    },
    "pf1": {
      "migration": "11.0"
    }
  },
  "_stats": {
    "coreVersion": "13.348",
    "systemId": "pf1",
    "systemVersion": "11.8",
    "createdTime": 1757274170799,
    "modifiedTime": 1757274170826,
    "lastModifiedBy": "8IbKpD2W58KL9Hzb",
    "exportSource": {
      "worldId": "shiptest",
      "uuid": "Item.mgLxCn0KNCM5yYnO",
      "coreVersion": "13.348",
      "systemId": "pf1",
      "systemVersion": "11.8"
    }
  },
  "ownership": {
    "default": 0
  }
}